{
"meta":{"test_sets":[],"test_metrics":[],"learn_metrics":[{"best_value":"Min","name":"RMSE"}],"launch_mode":"Train","parameters":"","iteration_count":100,"learn_sets":["learn"],"name":"experiment"},
"iterations":[
{"learn":[14.005006],"iteration":0,"passed_time":0.001004313216,"remaining_time":0.09942700843},
{"learn":[13.14441192],"iteration":1,"passed_time":0.002020626784,"remaining_time":0.09901071243},
{"learn":[12.34258257],"iteration":2,"passed_time":0.002881947499,"remaining_time":0.09318296915},
{"learn":[11.64527793],"iteration":3,"passed_time":0.003575503703,"remaining_time":0.08581208886},
{"learn":[11.02766183],"iteration":4,"passed_time":0.004381470543,"remaining_time":0.08324794032},
{"learn":[10.43485794],"iteration":5,"passed_time":0.005254460572,"remaining_time":0.0823198823},
{"learn":[9.890641275],"iteration":6,"passed_time":0.00612458622,"remaining_time":0.08136950263},
{"learn":[9.492161212],"iteration":7,"passed_time":0.006935821996,"remaining_time":0.07976195295},
{"learn":[9.105082953],"iteration":8,"passed_time":0.007741548428,"remaining_time":0.07827565633},
{"learn":[8.674157135],"iteration":9,"passed_time":0.008523514566,"remaining_time":0.0767116311},
{"learn":[8.341743544],"iteration":10,"passed_time":0.009331044057,"remaining_time":0.07549662919},
{"learn":[8.049372916],"iteration":11,"passed_time":0.0101562936,"remaining_time":0.07447948639},
{"learn":[7.757318612],"iteration":12,"passed_time":0.01093716788,"remaining_time":0.07319489277},
{"learn":[7.522206899],"iteration":13,"passed_time":0.01171606882,"remaining_time":0.07197013706},
{"learn":[7.297756655],"iteration":14,"passed_time":0.01252753499,"remaining_time":0.07098936495},
{"learn":[7.088359431],"iteration":15,"passed_time":0.01335221404,"remaining_time":0.07009912372},
{"learn":[6.882113791],"iteration":16,"passed_time":0.01439964037,"remaining_time":0.07030412653},
{"learn":[6.704728832],"iteration":17,"passed_time":0.0153120773,"remaining_time":0.06975501881},
{"learn":[6.563881962],"iteration":18,"passed_time":0.0162304648,"remaining_time":0.06919303413},
{"learn":[6.418790279],"iteration":19,"passed_time":0.01713375669,"remaining_time":0.06853502676},
{"learn":[6.315756953],"iteration":20,"passed_time":0.0179805127,"remaining_time":0.06764097637},
{"learn":[6.210157751],"iteration":21,"passed_time":0.01875819157,"remaining_time":0.06650631557},
{"learn":[6.115058449],"iteration":22,"passed_time":0.01957149085,"remaining_time":0.06552194762},
{"learn":[6.014819884],"iteration":23,"passed_time":0.0203939757,"remaining_time":0.06458092305},
{"learn":[5.93117229],"iteration":24,"passed_time":0.02120298771,"remaining_time":0.06360896312},
{"learn":[5.844857622],"iteration":25,"passed_time":0.02195745721,"remaining_time":0.06249430129},
{"learn":[5.771145213],"iteration":26,"passed_time":0.02273342317,"remaining_time":0.06146444043},
{"learn":[5.704018229],"iteration":27,"passed_time":0.0235502885,"remaining_time":0.06055788471},
{"learn":[5.665806474],"iteration":28,"passed_time":0.02432434121,"remaining_time":0.05955269745},
{"learn":[5.616500369],"iteration":29,"passed_time":0.02514936037,"remaining_time":0.05868184085},
{"learn":[5.558023666],"iteration":30,"passed_time":0.02598624011,"remaining_time":0.05784034088},
{"learn":[5.510080976],"iteration":31,"passed_time":0.02677994615,"remaining_time":0.05690738558},
{"learn":[5.468747792],"iteration":32,"passed_time":0.02759727226,"remaining_time":0.0560308255},
{"learn":[5.429275534],"iteration":33,"passed_time":0.02838515844,"remaining_time":0.05510060167},
{"learn":[5.402117324],"iteration":34,"passed_time":0.02947022861,"remaining_time":0.05473042456},
{"learn":[5.367635151],"iteration":35,"passed_time":0.03038926673,"remaining_time":0.05402536308},
{"learn":[5.345181232],"iteration":36,"passed_time":0.03123216621,"remaining_time":0.05317909381},
{"learn":[5.319151269],"iteration":37,"passed_time":0.03203227311,"remaining_time":0.05226318244},
{"learn":[5.296134146],"iteration":38,"passed_time":0.03281614247,"remaining_time":0.05132781259},
{"learn":[5.269629003],"iteration":39,"passed_time":0.03364163242,"remaining_time":0.05046244864},
{"learn":[5.251147059],"iteration":40,"passed_time":0.03445220708,"remaining_time":0.04957756628},
{"learn":[5.248003302],"iteration":41,"passed_time":0.03482506942,"remaining_time":0.04809176253},
{"learn":[5.232376509],"iteration":42,"passed_time":0.03563153711,"remaining_time":0.04723250268},
{"learn":[5.213524255],"iteration":43,"passed_time":0.03643465912,"remaining_time":0.04637138434},
{"learn":[5.189691584],"iteration":44,"passed_time":0.03722090251,"remaining_time":0.04549221418},
{"learn":[5.166052198],"iteration":45,"passed_time":0.0380132763,"remaining_time":0.04462428088},
{"learn":[5.140406659],"iteration":46,"passed_time":0.03880784381,"remaining_time":0.04376203664},
{"learn":[5.118929684],"iteration":47,"passed_time":0.03960168008,"remaining_time":0.04290182008},
{"learn":[5.108792602],"iteration":48,"passed_time":0.04038476812,"remaining_time":0.042033126},
{"learn":[5.098141225],"iteration":49,"passed_time":0.04122635584,"remaining_time":0.04122635584},
{"learn":[5.085926393],"iteration":50,"passed_time":0.04199387749,"remaining_time":0.04034705876},
{"learn":[5.067816804],"iteration":51,"passed_time":0.04276874158,"remaining_time":0.03947883838},
{"learn":[5.049834901],"iteration":52,"passed_time":0.04367233398,"remaining_time":0.03872829617},
{"learn":[5.03838627],"iteration":53,"passed_time":0.04454349138,"remaining_time":0.03794445562},
{"learn":[5.033534248],"iteration":54,"passed_time":0.04515530896,"remaining_time":0.03694525279},
{"learn":[5.023726885],"iteration":55,"passed_time":0.04596370993,"remaining_time":0.03611434352},
{"learn":[5.01290392],"iteration":56,"passed_time":0.04677712941,"remaining_time":0.03528800991},
{"learn":[5.005569127],"iteration":57,"passed_time":0.0475866022,"remaining_time":0.03445926366},
{"learn":[4.989969032],"iteration":58,"passed_time":0.04850607153,"remaining_time":0.03370760903},
{"learn":[4.976762446],"iteration":59,"passed_time":0.04931239898,"remaining_time":0.03287493265},
{"learn":[4.967222715],"iteration":60,"passed_time":0.05013107738,"remaining_time":0.03205101668},
{"learn":[4.954407599],"iteration":61,"passed_time":0.05094886426,"remaining_time":0.03122672326},
{"learn":[4.942125056],"iteration":62,"passed_time":0.05186314479,"remaining_time":0.03045930726},
{"learn":[4.930230716],"iteration":63,"passed_time":0.05274754465,"remaining_time":0.02967049386},
{"learn":[4.921695642],"iteration":64,"passed_time":0.05357323494,"remaining_time":0.0288471265},
{"learn":[4.906405625],"iteration":65,"passed_time":0.05439037072,"remaining_time":0.02801928189},
{"learn":[4.894330248],"iteration":66,"passed_time":0.05516726826,"remaining_time":0.0271719381},
{"learn":[4.88211557],"iteration":67,"passed_time":0.0559908049,"remaining_time":0.02634861407},
{"learn":[4.877946398],"iteration":68,"passed_time":0.05679717242,"remaining_time":0.02551757022},
{"learn":[4.863182126],"iteration":69,"passed_time":0.05757994993,"remaining_time":0.0246771214},
{"learn":[4.84646533],"iteration":70,"passed_time":0.05839031423,"remaining_time":0.02384956497},
{"learn":[4.838014752],"iteration":71,"passed_time":0.0594086312,"remaining_time":0.02310335658},
{"learn":[4.82981137],"iteration":72,"passed_time":0.06032469475,"remaining_time":0.0223118734},
{"learn":[4.817094767],"iteration":73,"passed_time":0.06116635212,"remaining_time":0.02149088047},
{"learn":[4.808314151],"iteration":74,"passed_time":0.06198992882,"remaining_time":0.02066330961},
{"learn":[4.796235023],"iteration":75,"passed_time":0.06289090679,"remaining_time":0.01986028636},
{"learn":[4.784434534],"iteration":76,"passed_time":0.06375034431,"remaining_time":0.01904231064},
{"learn":[4.774402487],"iteration":77,"passed_time":0.06456877229,"remaining_time":0.018211705},
{"learn":[4.76731896],"iteration":78,"passed_time":0.0654066232,"remaining_time":0.01738657072},
{"learn":[4.75934113],"iteration":79,"passed_time":0.06621063673,"remaining_time":0.01655265918},
{"learn":[4.754106378],"iteration":80,"passed_time":0.06697397127,"remaining_time":0.01570994388},
{"learn":[4.744002932],"iteration":81,"passed_time":0.06773756625,"remaining_time":0.01486922186},
{"learn":[4.731700554],"iteration":82,"passed_time":0.06853731254,"remaining_time":0.01403776281},
{"learn":[4.723284153],"iteration":83,"passed_time":0.06934891895,"remaining_time":0.01320931789},
{"learn":[4.712232782],"iteration":84,"passed_time":0.07015281227,"remaining_time":0.01237990805},
{"learn":[4.703046867],"iteration":85,"passed_time":0.07095374056,"remaining_time":0.01155060893},
{"learn":[4.698601855],"iteration":86,"passed_time":0.07175042166,"remaining_time":0.01072132737},
{"learn":[4.692429407],"iteration":87,"passed_time":0.07256574436,"remaining_time":0.009895328777},
{"learn":[4.675027364],"iteration":88,"passed_time":0.07341297118,"remaining_time":0.009073513292},
{"learn":[4.662368584],"iteration":89,"passed_time":0.07434878823,"remaining_time":0.00826097647},
{"learn":[4.646206172],"iteration":90,"passed_time":0.07520569146,"remaining_time":0.007437925529},
{"learn":[4.641245848],"iteration":91,"passed_time":0.07602984915,"remaining_time":0.00661129123},
{"learn":[4.633900435],"iteration":92,"passed_time":0.07696010677,"remaining_time":0.005792696209},
{"learn":[4.624738236],"iteration":93,"passed_time":0.07781761101,"remaining_time":0.004967081554},
{"learn":[4.612798287],"iteration":94,"passed_time":0.07864249994,"remaining_time":0.004139078944},
{"learn":[4.605222001],"iteration":95,"passed_time":0.07941089306,"remaining_time":0.003308787211},
{"learn":[4.601725912],"iteration":96,"passed_time":0.08013282739,"remaining_time":0.002478334868},
{"learn":[4.59722371],"iteration":97,"passed_time":0.08088668586,"remaining_time":0.001650748691},
{"learn":[4.580235665],"iteration":98,"passed_time":0.08170695696,"remaining_time":0.0008253227976},
{"learn":[4.57591791],"iteration":99,"passed_time":0.08251085029,"remaining_time":0}
]}